plottoolbox/CHANGELOG.md
plottoolbox/__init__.py
plottoolbox/_plotutils.py
plottoolbox/plottoolbox.py
plottoolbox/SciencePlots/setup.py
plottoolbox/SciencePlots/examples/plot-examples.py
plottoolbox/SciencePlots/scienceplots/__init__.py
plottoolbox/SciencePlots/scienceplots/styles/notebook.mplstyle
plottoolbox/SciencePlots/scienceplots/styles/scatter.mplstyle
plottoolbox/SciencePlots/scienceplots/styles/science.mplstyle
plottoolbox/SciencePlots/scienceplots/styles/color/bright.mplstyle
plottoolbox/SciencePlots/scienceplots/styles/color/high-contrast.mplstyle
plottoolbox/SciencePlots/scienceplots/styles/color/high-vis.mplstyle
plottoolbox/SciencePlots/scienceplots/styles/color/light.mplstyle
plottoolbox/SciencePlots/scienceplots/styles/color/muted.mplstyle
plottoolbox/SciencePlots/scienceplots/styles/color/retro.mplstyle
plottoolbox/SciencePlots/scienceplots/styles/color/std-colors.mplstyle
plottoolbox/SciencePlots/scienceplots/styles/color/vibrant.mplstyle
plottoolbox/SciencePlots/scienceplots/styles/journals/ieee.mplstyle
plottoolbox/SciencePlots/scienceplots/styles/journals/nature.mplstyle
plottoolbox/SciencePlots/scienceplots/styles/languages/cjk-jp-font.mplstyle
plottoolbox/SciencePlots/scienceplots/styles/languages/cjk-kr-font.mplstyle
plottoolbox/SciencePlots/scienceplots/styles/languages/cjk-sc-font.mplstyle
plottoolbox/SciencePlots/scienceplots/styles/languages/cjk-tc-font.mplstyle
plottoolbox/SciencePlots/scienceplots/styles/languages/russian-font.mplstyle
plottoolbox/SciencePlots/scienceplots/styles/languages/turkish-font.mplstyle
plottoolbox/SciencePlots/scienceplots/styles/misc/grid.mplstyle
plottoolbox/SciencePlots/scienceplots/styles/misc/latex-sans.mplstyle
plottoolbox/SciencePlots/scienceplots/styles/misc/no-latex.mplstyle
plottoolbox/SciencePlots/scienceplots/styles/misc/pgf.mplstyle
plottoolbox/SciencePlots/scienceplots/styles/misc/sans.mplstyle
plottoolbox/SkillMetrics/setup.py
plottoolbox/SkillMetrics/Examples/Farmington_River_data.py
plottoolbox-105.1.0.dist-info/licenses/LICENSE.txt
plottoolbox-105.1.0.dist-info/METADATA
plottoolbox-105.1.0.dist-info/WHEEL
plottoolbox-105.1.0.dist-info/entry_points.txt
plottoolbox-105.1.0.dist-info/top_level.txt
plottoolbox-105.1.0.dist-info/RECORD
